{
    "$schema": "https://schema.management.azure.com/schemas/2019-04-01/deploymentTemplate.json#",
    "contentVersion": "1.0.0.0",
    "parameters": {
        "name": {
            "type": "String"
        }
    },
    "resources": [
        {
            "type": "Microsoft.Web/serverfarms",
            "sku": {
                "name": "B1",
                "tier": "Basic",
                "size": "B1",
                "family": "B",
                "capacity": 1
            },
            "kind": "app",
            "name": "[parameters('name')]",
            "apiVersion": "2020-12-01",
            "location": "[resourceGroup().location]",
            "properties": {
                "name": "[parameters('name')]",
                "perSiteScaling": false,
                "reserved": false,
                "targetWorkerCount": 0,
                "targetWorkerSizeId": 0
            }
        }
    ]
}